AinaTheme/__init__.py
AinaTheme/aina_class.py
AinaTheme/utils/__init__.py
AinaTheme/utils/custom_colors.py
aina_gradio_theme-2.3.dist-info/LICENSE
aina_gradio_theme-2.3.dist-info/METADATA
aina_gradio_theme-2.3.dist-info/WHEEL
aina_gradio_theme-2.3.dist-info/top_level.txt
aina_gradio_theme-2.3.dist-info/RECORD
