Metadata-Version: 2.1
Name: aina-gradio-theme
Version: 2.3
Summary: Aina Theme is a custom Gradio theme inspired by the visual style of Storj theme. Feel free to use this theme to create Gradio apps that have a visual connection to the world of cloud technology.
Home-page: https://github.com/projecte-aina/aina-gradio-theme
Author: Projecte Aina
Author-email: aina@bsc.es
License: Apache License 2.0
License-File: LICENSE
